fourierassets/__init__.py
fourierassets/cli.py
fourierassets/completion.py
fourierassets/config.py
fourierassets/defaults.py
fourierassets/downloader.py
fourierassets/exceptions.py
fourierassets/lister.py
fourierassets/logger.py
fourierassets/rclone_client.py
fourierassets/rclone_installer.py
fourierassets/remover.py
fourierassets/uploader.py
fourierassets/utils.py
simassets/__init__.py
simassets/cli.py
fourierassets-0.1.5.dist-info/METADATA
fourierassets-0.1.5.dist-info/WHEEL
fourierassets-0.1.5.dist-info/entry_points.txt
fourierassets-0.1.5.dist-info/RECORD
