Metadata-Version: 2.4
Name: fourierassets
Version: 0.1.5
Summary: A package for managing robot simulation assets
Requires-Python: >=3.8
Requires-Dist: argcomplete
Requires-Dist: rclone-python==0.1.23
Requires-Dist: tqdm
